wandbot/__init__.py
wandbot/utils.py
wandbot/wandbot_tool.py
wandbot/api/__init__.py
wandbot/api/app.py
wandbot/api/client.py
wandbot/api/routers/__init__.py
wandbot/api/routers/chat.py
wandbot/api/routers/database.py
wandbot/api/routers/retrieve.py
wandbot/apps/__init__.py
wandbot/apps/utils.py
wandbot/apps/discord/__init__.py
wandbot/apps/discord/__main__.py
wandbot/apps/discord/config.py
wandbot/apps/slack/__init__.py
wandbot/apps/slack/__main__.py
wandbot/apps/slack/config.py
wandbot/apps/slack/formatter.py
wandbot/chat/__init__.py
wandbot/chat/chat.py
wandbot/chat/rag.py
wandbot/chat/schemas.py
wandbot/chat/utils.py
wandbot/configs/__init__.py
wandbot/configs/app_config.py
wandbot/configs/chat_config.py
wandbot/configs/database_config.py
wandbot/configs/ingestion_config.py
wandbot/configs/vector_store_config.py
wandbot/database/__init__.py
wandbot/database/client.py
wandbot/database/config.py
wandbot/database/database.py
wandbot/database/models.py
wandbot/database/schemas.py
wandbot/evaluation/__init__.py
wandbot/evaluation/eval.py
wandbot/evaluation/eval_config.py
wandbot/evaluation/eval_metrics/correctness.py
wandbot/evaluation/utils/jp_evaluation_dataprep.py
wandbot/evaluation/utils/jp_evaluation_dataupload.py
wandbot/evaluation/utils/log_data.py
wandbot/evaluation/utils/utils.py
wandbot/ingestion/__init__.py
wandbot/ingestion/__main__.py
wandbot/ingestion/prepare_data.py
wandbot/ingestion/preprocess_data.py
wandbot/ingestion/run_ingestion_config.py
wandbot/ingestion/utils.py
wandbot/ingestion/vectorstore_and_report.py
wandbot/ingestion/preprocessors/markdown.py
wandbot/ingestion/preprocessors/source_code.py
wandbot/models/embedding.py
wandbot/models/llm.py
wandbot/rag/__init__.py
wandbot/rag/query_handler.py
wandbot/rag/response_synthesis.py
wandbot/rag/retrieval.py
wandbot/rag/utils.py
wandbot/retriever/__init__.py
wandbot/retriever/base.py
wandbot/retriever/chroma.py
wandbot/retriever/mmr.py
wandbot/retriever/utils.py
wandbot/retriever/web_search.py
wandbot-1.3.2.dist-info/licenses/LICENSE
wandbot-1.3.2.dist-info/METADATA
wandbot-1.3.2.dist-info/WHEEL
wandbot-1.3.2.dist-info/top_level.txt
wandbot-1.3.2.dist-info/RECORD
