Metadata-Version: 2.4
Name: wandbot
Version: 1.3.2
Summary: WandBot is a Q&A bot for Weights & Biases Models and Weave documentation
Author-email: parambharat <bharat.ramanathan@wandb.com>, morganmcg1 <morganmcg1@users.noreply.github.com>, ayulockin <ayusht@wandb.com>, ash0ts <anish@wandb.com>
License:                                  Apache License
Project-URL: Homepage, https://github.com/wandb/wandbot
Project-URL: Repository, https://github.com/wandb/wandbot
Classifier: Programming Language :: Python :: 3
Requires-Python: <3.14,>=3.11
License-File: LICENSE
Provides-Extra: core
Requires-Dist: pandas>=2.1.2; extra == "core"
Requires-Dist: pydantic>=2.10.0; extra == "core"
Requires-Dist: pydantic-settings>=2.5.1; extra == "core"
Requires-Dist: gitpython>=3.1.40; extra == "core"
Requires-Dist: giturlparse>=0.12.0; extra == "core"
Requires-Dist: scikit-learn>=1.3.2; extra == "core"
Requires-Dist: python-dotenv>=1.0.0; extra == "core"
Requires-Dist: slack-bolt>=1.18.0; extra == "core"
Requires-Dist: slack-sdk>=3.21.3; extra == "core"
Requires-Dist: discord>=2.3.2; extra == "core"
Requires-Dist: markdown>=3.5.1; extra == "core"
Requires-Dist: fastapi>=0.115.0; extra == "core"
Requires-Dist: uvicorn>=0.24.0; extra == "core"
Requires-Dist: openai>=1.71.0; extra == "core"
Requires-Dist: anthropic>=0.49.0; extra == "core"
Requires-Dist: google-genai>=1.9.0; extra == "core"
Requires-Dist: cohere>=5.13.0; extra == "core"
Requires-Dist: langchain>=0.2.2; extra == "core"
Requires-Dist: langchain-core>=0.2.2; extra == "core"
Requires-Dist: chromadb>=1.0.3; extra == "core"
Requires-Dist: weave>=0.51.41; extra == "core"
Requires-Dist: wandb[workspaces]>=0.19.9; extra == "core"
Requires-Dist: tiktoken; extra == "core"
Requires-Dist: fasttext-wheel; extra == "core"
Requires-Dist: nest_asyncio>=1.6.0; extra == "core"
Requires-Dist: google-cloud-bigquery>=3.14.1; extra == "core"
Requires-Dist: db-dtypes>=1.2.0; extra == "core"
Requires-Dist: nbformat>=5.10.4; extra == "core"
Requires-Dist: nbconvert>=7.16.4; extra == "core"
Requires-Dist: typing_extensions>=4.12.0; extra == "core"
Dynamic: license-file
